{
  "tier": 34,
  "seed": 340113,
  "description": "Tier 34 randomly generated fixture (seed 340113)",
  "input": {
    "id": "root-node",
    "padding": {
      "top": 14,
      "right": 9,
      "bottom": 6,
      "left": 10
    },
    "margin": {
      "top": 9,
      "right": 0,
      "bottom": 6,
      "left": 6
    },
    "border": {
      "top": 0,
      "right": 6,
      "bottom": 4,
      "left": 8
    },
    "boxSizing": "border-box",
    "display": "flex",
    "children": [
      {
        "id": "node-2",
        "padding": {
          "top": 7,
          "right": 11,
          "bottom": 6,
          "left": 1
        },
        "margin": {
          "top": 2,
          "right": 18,
          "bottom": 15,
          "left": 9
        },
        "border": {
          "top": 7,
          "right": 8,
          "bottom": 10,
          "left": 1
        },
        "boxSizing": "content-box",
        "display": "flex",
        "children": [
          {
            "id": "node-3",
            "padding": {
              "top": 15,
              "right": 18,
              "bottom": 14,
              "left": 16
            },
            "margin": {
              "top": 9,
              "right": 11,
              "bottom": 15,
              "left": 14
            },
            "border": {
              "top": 6,
              "right": 10,
              "bottom": 10,
              "left": 1
            },
            "boxSizing": "border-box",
            "display": "block",
            "children": [],
            "width": 77,
            "height": 48,
            "flexShrink": 1
          },
          {
            "id": "node-4",
            "padding": {
              "top": 10,
              "right": 13,
              "bottom": 6,
              "left": 11
            },
            "margin": {
              "top": 7,
              "right": 16,
              "bottom": 7,
              "left": 6
            },
            "border": {
              "top": 6,
              "right": 3,
              "bottom": 9,
              "left": 2
            },
            "boxSizing": "border-box",
            "display": "block",
            "children": [],
            "width": 63,
            "height": 60,
            "flexShrink": 0
          },
          {
            "id": "node-5",
            "padding": {
              "top": 13,
              "right": 8,
              "bottom": 7,
              "left": 14
            },
            "margin": {
              "top": 17,
              "right": 2,
              "bottom": 20,
              "left": 14
            },
            "border": {
              "top": 1,
              "right": 10,
              "bottom": 4,
              "left": 9
            },
            "boxSizing": "content-box",
            "display": "block",
            "children": [],
            "width": 55,
            "height": 46,
            "flexShrink": 1
          },
          {
            "id": "node-6",
            "padding": {
              "top": 2,
              "right": 19,
              "bottom": 11,
              "left": 19
            },
            "margin": {
              "top": 2,
              "right": 13,
              "bottom": 5,
              "left": 13
            },
            "border": {
              "top": 5,
              "right": 5,
              "bottom": 9,
              "left": 6
            },
            "boxSizing": "content-box",
            "display": "block",
            "children": [],
            "width": 50,
            "height": 33,
            "flexShrink": 0
          }
        ],
        "flexDirection": "column",
        "minHeight": "max-content",
        "height": 23
      },
      {
        "id": "node-7",
        "padding": {
          "top": 7,
          "right": 2,
          "bottom": 3,
          "left": 7
        },
        "margin": {
          "top": 7,
          "right": 7,
          "bottom": 16,
          "left": 10
        },
        "border": {
          "top": 6,
          "right": 0,
          "bottom": 10,
          "left": 2
        },
        "boxSizing": "content-box",
        "display": "flex",
        "children": [
          {
            "id": "node-8",
            "padding": {
              "top": 5,
              "right": 2,
              "bottom": 15,
              "left": 1
            },
            "margin": {
              "top": 14,
              "right": 8,
              "bottom": 5,
              "left": 17
            },
            "border": {
              "top": 4,
              "right": 3,
              "bottom": 10,
              "left": 1
            },
            "boxSizing": "border-box",
            "display": "block",
            "children": [],
            "width": 51,
            "height": 21,
            "flexShrink": 0
          },
          {
            "id": "node-9",
            "padding": {
              "top": 11,
              "right": 10,
              "bottom": 6,
              "left": 20
            },
            "margin": {
              "top": 0,
              "right": 14,
              "bottom": 20,
              "left": 18
            },
            "border": {
              "top": 10,
              "right": 0,
              "bottom": 6,
              "left": 6
            },
            "boxSizing": "content-box",
            "display": "block",
            "children": [],
            "width": 67,
            "height": 55,
            "flexShrink": 1
          },
          {
            "id": "node-10",
            "padding": {
              "top": 5,
              "right": 6,
              "bottom": 9,
              "left": 20
            },
            "margin": {
              "top": 6,
              "right": 15,
              "bottom": 4,
              "left": 5
            },
            "border": {
              "top": 1,
              "right": 3,
              "bottom": 6,
              "left": 1
            },
            "boxSizing": "border-box",
            "display": "block",
            "children": [],
            "width": 76,
            "height": 60,
            "flexShrink": 0
          },
          {
            "id": "node-11",
            "padding": {
              "top": 2,
              "right": 4,
              "bottom": 8,
              "left": 2
            },
            "margin": {
              "top": 5,
              "right": 7,
              "bottom": 4,
              "left": 9
            },
            "border": {
              "top": 3,
              "right": 7,
              "bottom": 2,
              "left": 7
            },
            "boxSizing": "content-box",
            "display": "block",
            "children": [],
            "width": 36,
            "height": 56,
            "flexShrink": 1
          },
          {
            "id": "node-12",
            "padding": {
              "top": 8,
              "right": 7,
              "bottom": 6,
              "left": 11
            },
            "margin": {
              "top": 9,
              "right": 18,
              "bottom": 20,
              "left": 13
            },
            "border": {
              "top": 0,
              "right": 0,
              "bottom": 3,
              "left": 1
            },
            "boxSizing": "content-box",
            "display": "block",
            "children": [],
            "width": 87,
            "height": 44,
            "flexShrink": 0
          }
        ],
        "flexDirection": "column",
        "minHeight": "min-content",
        "flexShrink": 1
      },
      {
        "id": "node-13",
        "padding": {
          "top": 18,
          "right": 18,
          "bottom": 15,
          "left": 11
        },
        "margin": {
          "top": 8,
          "right": 15,
          "bottom": 8,
          "left": 11
        },
        "border": {
          "top": 6,
          "right": 9,
          "bottom": 8,
          "left": 6
        },
        "boxSizing": "content-box",
        "display": "flex",
        "children": [
          {
            "id": "node-14",
            "padding": {
              "top": 17,
              "right": 20,
              "bottom": 15,
              "left": 8
            },
            "margin": {
              "top": 19,
              "right": 6,
              "bottom": 2,
              "left": 2
            },
            "border": {
              "top": 10,
              "right": 4,
              "bottom": 0,
              "left": 1
            },
            "boxSizing": "border-box",
            "display": "block",
            "children": [],
            "width": 34,
            "height": 29,
            "flexShrink": 0
          },
          {
            "id": "node-15",
            "padding": {
              "top": 13,
              "right": 13,
              "bottom": 14,
              "left": 2
            },
            "margin": {
              "top": 16,
              "right": 6,
              "bottom": 20,
              "left": 2
            },
            "border": {
              "top": 6,
              "right": 6,
              "bottom": 0,
              "left": 10
            },
            "boxSizing": "content-box",
            "display": "block",
            "children": [],
            "width": 86,
            "height": 51,
            "flexShrink": 1
          },
          {
            "id": "node-16",
            "padding": {
              "top": 5,
              "right": 9,
              "bottom": 6,
              "left": 8
            },
            "margin": {
              "top": 9,
              "right": 3,
              "bottom": 16,
              "left": 3
            },
            "border": {
              "top": 10,
              "right": 9,
              "bottom": 0,
              "left": 10
            },
            "boxSizing": "border-box",
            "display": "block",
            "children": [],
            "width": 56,
            "height": 48,
            "flexShrink": 0
          },
          {
            "id": "node-17",
            "padding": {
              "top": 17,
              "right": 11,
              "bottom": 3,
              "left": 12
            },
            "margin": {
              "top": 18,
              "right": 1,
              "bottom": 3,
              "left": 3
            },
            "border": {
              "top": 7,
              "right": 10,
              "bottom": 9,
              "left": 5
            },
            "boxSizing": "content-box",
            "display": "block",
            "children": [],
            "width": 46,
            "height": 55,
            "flexShrink": 1
          },
          {
            "id": "node-18",
            "padding": {
              "top": 18,
              "right": 4,
              "bottom": 16,
              "left": 2
            },
            "margin": {
              "top": 0,
              "right": 12,
              "bottom": 8,
              "left": 13
            },
            "border": {
              "top": 8,
              "right": 0,
              "bottom": 5,
              "left": 6
            },
            "boxSizing": "border-box",
            "display": "block",
            "children": [],
            "width": 32,
            "height": 44,
            "flexShrink": 0
          }
        ],
        "flexDirection": "column",
        "maxHeight": "min-content",
        "flexGrow": 0
      }
    ],
    "flexDirection": "column",
    "flexWrap": "nowrap",
    "width": 291,
    "height": 368,
    "alignItems": "stretch",
    "gap": 12
  },
  "expected": {
    "root-node": {
      "id": "root-node",
      "x": -18,
      "y": -14,
      "width": 258,
      "height": 344,
      "padding": {
        "top": 14,
        "right": 9,
        "bottom": 6,
        "left": 10
      },
      "border": {
        "top": 0,
        "right": 6,
        "bottom": 4,
        "left": 8
      },
      "margin": {
        "top": 9,
        "right": 0,
        "bottom": 6,
        "left": 6
      },
      "borderBoxWidth": 291,
      "borderBoxHeight": 368,
      "outerWidth": 297,
      "outerHeight": 383
    },
    "node-2": {
      "id": "node-2",
      "x": 9,
      "y": 2,
      "width": 210,
      "height": 321,
      "padding": {
        "top": 7,
        "right": 11,
        "bottom": 6,
        "left": 1
      },
      "border": {
        "top": 7,
        "right": 8,
        "bottom": 10,
        "left": 1
      },
      "margin": {
        "top": 2,
        "right": 18,
        "bottom": 15,
        "left": 9
      },
      "borderBoxWidth": 231,
      "borderBoxHeight": 351,
      "outerWidth": 258,
      "outerHeight": 368
    },
    "node-3": {
      "id": "node-3",
      "x": 25,
      "y": 25,
      "width": 32,
      "height": 3,
      "padding": {
        "top": 15,
        "right": 18,
        "bottom": 14,
        "left": 16
      },
      "border": {
        "top": 6,
        "right": 10,
        "bottom": 10,
        "left": 1
      },
      "margin": {
        "top": 9,
        "right": 11,
        "bottom": 15,
        "left": 14
      },
      "borderBoxWidth": 77,
      "borderBoxHeight": 48,
      "outerWidth": 102,
      "outerHeight": 72
    },
    "node-4": {
      "id": "node-4",
      "x": 17,
      "y": 95,
      "width": 34,
      "height": 29,
      "padding": {
        "top": 10,
        "right": 13,
        "bottom": 6,
        "left": 11
      },
      "border": {
        "top": 6,
        "right": 3,
        "bottom": 9,
        "left": 2
      },
      "margin": {
        "top": 7,
        "right": 16,
        "bottom": 7,
        "left": 6
      },
      "borderBoxWidth": 63,
      "borderBoxHeight": 60,
      "outerWidth": 85,
      "outerHeight": 74
    },
    "node-5": {
      "id": "node-5",
      "x": 25,
      "y": 179,
      "width": 55,
      "height": 46,
      "padding": {
        "top": 13,
        "right": 8,
        "bottom": 7,
        "left": 14
      },
      "border": {
        "top": 1,
        "right": 10,
        "bottom": 4,
        "left": 9
      },
      "margin": {
        "top": 17,
        "right": 2,
        "bottom": 20,
        "left": 14
      },
      "borderBoxWidth": 96,
      "borderBoxHeight": 71,
      "outerWidth": 112,
      "outerHeight": 108
    },
    "node-6": {
      "id": "node-6",
      "x": 24,
      "y": 272,
      "width": 50,
      "height": 33,
      "padding": {
        "top": 2,
        "right": 19,
        "bottom": 11,
        "left": 19
      },
      "border": {
        "top": 5,
        "right": 5,
        "bottom": 9,
        "left": 6
      },
      "margin": {
        "top": 2,
        "right": 13,
        "bottom": 5,
        "left": 13
      },
      "borderBoxWidth": 99,
      "borderBoxHeight": 60,
      "outerWidth": 125,
      "outerHeight": 67
    },
    "node-7": {
      "id": "node-7",
      "x": 10,
      "y": 387,
      "width": 230,
      "height": 401,
      "padding": {
        "top": 7,
        "right": 2,
        "bottom": 3,
        "left": 7
      },
      "border": {
        "top": 6,
        "right": 0,
        "bottom": 10,
        "left": 2
      },
      "margin": {
        "top": 7,
        "right": 7,
        "bottom": 16,
        "left": 10
      },
      "borderBoxWidth": 241,
      "borderBoxHeight": 427,
      "outerWidth": 258,
      "outerHeight": 450
    },
    "node-8": {
      "id": "node-8",
      "x": 36,
      "y": 414,
      "width": 44,
      "height": 0,
      "padding": {
        "top": 5,
        "right": 2,
        "bottom": 15,
        "left": 1
      },
      "border": {
        "top": 4,
        "right": 3,
        "bottom": 10,
        "left": 1
      },
      "margin": {
        "top": 14,
        "right": 8,
        "bottom": 5,
        "left": 17
      },
      "borderBoxWidth": 51,
      "borderBoxHeight": 34,
      "outerWidth": 76,
      "outerHeight": 53
    },
    "node-9": {
      "id": "node-9",
      "x": 37,
      "y": 453,
      "width": 67,
      "height": 55,
      "padding": {
        "top": 11,
        "right": 10,
        "bottom": 6,
        "left": 20
      },
      "border": {
        "top": 10,
        "right": 0,
        "bottom": 6,
        "left": 6
      },
      "margin": {
        "top": 0,
        "right": 14,
        "bottom": 20,
        "left": 18
      },
      "borderBoxWidth": 103,
      "borderBoxHeight": 88,
      "outerWidth": 135,
      "outerHeight": 108
    },
    "node-10": {
      "id": "node-10",
      "x": 24,
      "y": 567,
      "width": 46,
      "height": 39,
      "padding": {
        "top": 5,
        "right": 6,
        "bottom": 9,
        "left": 20
      },
      "border": {
        "top": 1,
        "right": 3,
        "bottom": 6,
        "left": 1
      },
      "margin": {
        "top": 6,
        "right": 15,
        "bottom": 4,
        "left": 5
      },
      "borderBoxWidth": 76,
      "borderBoxHeight": 60,
      "outerWidth": 96,
      "outerHeight": 70
    },
    "node-11": {
      "id": "node-11",
      "x": 28,
      "y": 636,
      "width": 36,
      "height": 56,
      "padding": {
        "top": 2,
        "right": 4,
        "bottom": 8,
        "left": 2
      },
      "border": {
        "top": 3,
        "right": 7,
        "bottom": 2,
        "left": 7
      },
      "margin": {
        "top": 5,
        "right": 7,
        "bottom": 4,
        "left": 9
      },
      "borderBoxWidth": 56,
      "borderBoxHeight": 71,
      "outerWidth": 72,
      "outerHeight": 80
    },
    "node-12": {
      "id": "node-12",
      "x": 32,
      "y": 720,
      "width": 87,
      "height": 44,
      "padding": {
        "top": 8,
        "right": 7,
        "bottom": 6,
        "left": 11
      },
      "border": {
        "top": 0,
        "right": 0,
        "bottom": 3,
        "left": 1
      },
      "margin": {
        "top": 9,
        "right": 18,
        "bottom": 20,
        "left": 13
      },
      "borderBoxWidth": 106,
      "borderBoxHeight": 61,
      "outerWidth": 137,
      "outerHeight": 90
    },
    "node-13": {
      "id": "node-13",
      "x": 11,
      "y": 850,
      "width": 188,
      "height": 423,
      "padding": {
        "top": 18,
        "right": 18,
        "bottom": 15,
        "left": 11
      },
      "border": {
        "top": 6,
        "right": 9,
        "bottom": 8,
        "left": 6
      },
      "margin": {
        "top": 8,
        "right": 15,
        "bottom": 8,
        "left": 11
      },
      "borderBoxWidth": 232,
      "borderBoxHeight": 470,
      "outerWidth": 258,
      "outerHeight": 486
    },
    "node-14": {
      "id": "node-14",
      "x": 30,
      "y": 893,
      "width": 1,
      "height": 0,
      "padding": {
        "top": 17,
        "right": 20,
        "bottom": 15,
        "left": 8
      },
      "border": {
        "top": 10,
        "right": 4,
        "bottom": 0,
        "left": 1
      },
      "margin": {
        "top": 19,
        "right": 6,
        "bottom": 2,
        "left": 2
      },
      "borderBoxWidth": 34,
      "borderBoxHeight": 42,
      "outerWidth": 42,
      "outerHeight": 63
    },
    "node-15": {
      "id": "node-15",
      "x": 30,
      "y": 953,
      "width": 86,
      "height": 51,
      "padding": {
        "top": 13,
        "right": 13,
        "bottom": 14,
        "left": 2
      },
      "border": {
        "top": 6,
        "right": 6,
        "bottom": 0,
        "left": 10
      },
      "margin": {
        "top": 16,
        "right": 6,
        "bottom": 20,
        "left": 2
      },
      "borderBoxWidth": 117,
      "borderBoxHeight": 84,
      "outerWidth": 125,
      "outerHeight": 120
    },
    "node-16": {
      "id": "node-16",
      "x": 31,
      "y": 1066,
      "width": 20,
      "height": 27,
      "padding": {
        "top": 5,
        "right": 9,
        "bottom": 6,
        "left": 8
      },
      "border": {
        "top": 10,
        "right": 9,
        "bottom": 0,
        "left": 10
      },
      "margin": {
        "top": 9,
        "right": 3,
        "bottom": 16,
        "left": 3
      },
      "borderBoxWidth": 56,
      "borderBoxHeight": 48,
      "outerWidth": 62,
      "outerHeight": 73
    },
    "node-17": {
      "id": "node-17",
      "x": 31,
      "y": 1148,
      "width": 46,
      "height": 55,
      "padding": {
        "top": 17,
        "right": 11,
        "bottom": 3,
        "left": 12
      },
      "border": {
        "top": 7,
        "right": 10,
        "bottom": 9,
        "left": 5
      },
      "margin": {
        "top": 18,
        "right": 1,
        "bottom": 3,
        "left": 3
      },
      "borderBoxWidth": 84,
      "borderBoxHeight": 91,
      "outerWidth": 88,
      "outerHeight": 112
    },
    "node-18": {
      "id": "node-18",
      "x": 41,
      "y": 1242,
      "width": 20,
      "height": 0,
      "padding": {
        "top": 18,
        "right": 4,
        "bottom": 16,
        "left": 2
      },
      "border": {
        "top": 8,
        "right": 0,
        "bottom": 5,
        "left": 6
      },
      "margin": {
        "top": 0,
        "right": 12,
        "bottom": 8,
        "left": 13
      },
      "borderBoxWidth": 32,
      "borderBoxHeight": 47,
      "outerWidth": 57,
      "outerHeight": 55
    }
  },
  "chromiumVersion": "Chrome/146.0.7680.153",
  "tolerance": 0.5
}