{
  "tier": 17,
  "seed": 170044,
  "description": "Tier 17 randomly generated fixture (seed 170044)",
  "input": {
    "id": "root-node",
    "padding": {
      "top": 20,
      "right": 2,
      "bottom": 10,
      "left": 8
    },
    "margin": {
      "top": 0,
      "right": 15,
      "bottom": 0,
      "left": 6
    },
    "border": {
      "top": 10,
      "right": 8,
      "bottom": 10,
      "left": 5
    },
    "boxSizing": "content-box",
    "display": "flex",
    "children": [
      {
        "id": "node-2",
        "padding": {
          "top": 12,
          "right": 12,
          "bottom": 16,
          "left": 7
        },
        "margin": {
          "top": 0,
          "right": 6,
          "bottom": 0,
          "left": 7
        },
        "border": {
          "top": 1,
          "right": 1,
          "bottom": 9,
          "left": 5
        },
        "boxSizing": "content-box",
        "display": "flex",
        "children": [
          {
            "id": "node-3",
            "padding": {
              "top": 12,
              "right": 0,
              "bottom": 16,
              "left": 14
            },
            "margin": {
              "top": 0,
              "right": 8,
              "bottom": 0,
              "left": 6
            },
            "border": {
              "top": 2,
              "right": 0,
              "bottom": 5,
              "left": 8
            },
            "boxSizing": "content-box",
            "display": "block",
            "children": [
              {
                "id": "node-4",
                "padding": {
                  "top": 11,
                  "right": 4,
                  "bottom": 3,
                  "left": 10
                },
                "margin": {
                  "top": 0,
                  "right": 7,
                  "bottom": 0,
                  "left": 10
                },
                "border": {
                  "top": 3,
                  "right": 2,
                  "bottom": 4,
                  "left": 3
                },
                "boxSizing": "border-box",
                "display": "block",
                "children": [],
                "width": 85,
                "height": 21,
                "flexGrow": 1,
                "flexShrink": 1
              }
            ],
            "width": 78,
            "height": 86,
            "flexGrow": 0,
            "flexShrink": 0
          },
          {
            "id": "node-5",
            "padding": {
              "top": 8,
              "right": 6,
              "bottom": 9,
              "left": 5
            },
            "margin": {
              "top": 0,
              "right": 4,
              "bottom": 0,
              "left": 11
            },
            "border": {
              "top": 2,
              "right": 3,
              "bottom": 2,
              "left": 9
            },
            "boxSizing": "content-box",
            "display": "block",
            "children": [
              {
                "id": "node-6",
                "padding": {
                  "top": 3,
                  "right": 6,
                  "bottom": 13,
                  "left": 19
                },
                "margin": {
                  "top": 0,
                  "right": 20,
                  "bottom": 0,
                  "left": 11
                },
                "border": {
                  "top": 0,
                  "right": 2,
                  "bottom": 10,
                  "left": 2
                },
                "boxSizing": "border-box",
                "display": "block",
                "children": [],
                "width": 89,
                "height": 61,
                "flexGrow": 0,
                "flexShrink": 1
              },
              {
                "id": "node-7",
                "padding": {
                  "top": 17,
                  "right": 5,
                  "bottom": 16,
                  "left": 11
                },
                "margin": {
                  "top": 0,
                  "right": 14,
                  "bottom": 0,
                  "left": 9
                },
                "border": {
                  "top": 8,
                  "right": 1,
                  "bottom": 6,
                  "left": 6
                },
                "boxSizing": "border-box",
                "display": "block",
                "children": [],
                "width": 46,
                "height": 73,
                "flexGrow": 1,
                "flexShrink": 1
              }
            ],
            "width": 99,
            "height": 71,
            "flexGrow": 1,
            "flexShrink": 0
          },
          {
            "id": "node-8",
            "padding": {
              "top": 9,
              "right": 2,
              "bottom": 17,
              "left": 0
            },
            "margin": {
              "top": 0,
              "right": 6,
              "bottom": 0,
              "left": 5
            },
            "border": {
              "top": 5,
              "right": 10,
              "bottom": 1,
              "left": 8
            },
            "boxSizing": "content-box",
            "display": "block",
            "children": [
              {
                "id": "node-9",
                "padding": {
                  "top": 20,
                  "right": 18,
                  "bottom": 16,
                  "left": 9
                },
                "margin": {
                  "top": 0,
                  "right": 17,
                  "bottom": 0,
                  "left": 0
                },
                "border": {
                  "top": 0,
                  "right": 7,
                  "bottom": 6,
                  "left": 10
                },
                "boxSizing": "content-box",
                "display": "flex",
                "children": [],
                "width": 85,
                "height": 21,
                "flexGrow": 1,
                "flexShrink": 0
              },
              {
                "id": "node-10",
                "padding": {
                  "top": 8,
                  "right": 11,
                  "bottom": 13,
                  "left": 16
                },
                "margin": {
                  "top": 0,
                  "right": 5,
                  "bottom": 0,
                  "left": 13
                },
                "border": {
                  "top": 6,
                  "right": 3,
                  "bottom": 10,
                  "left": 0
                },
                "boxSizing": "content-box",
                "display": "block",
                "children": [],
                "width": 24,
                "height": 79,
                "flexGrow": 0,
                "flexShrink": 0
              }
            ],
            "width": 119,
            "height": 120,
            "flexGrow": 1,
            "flexShrink": 0
          }
        ],
        "flexDirection": "row",
        "width": 197,
        "height": 126,
        "flexGrow": 0,
        "flexShrink": 0
      }
    ],
    "flexDirection": "row",
    "flexWrap": "nowrap",
    "width": 755,
    "height": 534
  },
  "expected": {
    "root-node": {
      "id": "root-node",
      "x": -13,
      "y": -30,
      "width": 755,
      "height": 534,
      "padding": {
        "top": 20,
        "right": 2,
        "bottom": 10,
        "left": 8
      },
      "border": {
        "top": 10,
        "right": 8,
        "bottom": 10,
        "left": 5
      },
      "margin": {
        "top": 0,
        "right": 15,
        "bottom": 0,
        "left": 6
      },
      "borderBoxWidth": 778,
      "borderBoxHeight": 584,
      "outerWidth": 799,
      "outerHeight": 584
    },
    "node-2": {
      "id": "node-2",
      "x": 7,
      "y": 0,
      "width": 197,
      "height": 126,
      "padding": {
        "top": 12,
        "right": 12,
        "bottom": 16,
        "left": 7
      },
      "border": {
        "top": 1,
        "right": 1,
        "bottom": 9,
        "left": 5
      },
      "margin": {
        "top": 0,
        "right": 6,
        "bottom": 0,
        "left": 7
      },
      "borderBoxWidth": 222,
      "borderBoxHeight": 164,
      "outerWidth": 235,
      "outerHeight": 164
    },
    "node-3": {
      "id": "node-3",
      "x": 25,
      "y": 13,
      "width": 78,
      "height": 86,
      "padding": {
        "top": 12,
        "right": 0,
        "bottom": 16,
        "left": 14
      },
      "border": {
        "top": 2,
        "right": 0,
        "bottom": 5,
        "left": 8
      },
      "margin": {
        "top": 0,
        "right": 8,
        "bottom": 0,
        "left": 6
      },
      "borderBoxWidth": 100,
      "borderBoxHeight": 121,
      "outerWidth": 114,
      "outerHeight": 121
    },
    "node-4": {
      "id": "node-4",
      "x": 57,
      "y": 27,
      "width": 66,
      "height": 0,
      "padding": {
        "top": 11,
        "right": 4,
        "bottom": 3,
        "left": 10
      },
      "border": {
        "top": 3,
        "right": 2,
        "bottom": 4,
        "left": 3
      },
      "margin": {
        "top": 0,
        "right": 7,
        "bottom": 0,
        "left": 10
      },
      "borderBoxWidth": 85,
      "borderBoxHeight": 21,
      "outerWidth": 102,
      "outerHeight": 21
    },
    "node-5": {
      "id": "node-5",
      "x": 144,
      "y": 13,
      "width": 99,
      "height": 71,
      "padding": {
        "top": 8,
        "right": 6,
        "bottom": 9,
        "left": 5
      },
      "border": {
        "top": 2,
        "right": 3,
        "bottom": 2,
        "left": 9
      },
      "margin": {
        "top": 0,
        "right": 4,
        "bottom": 0,
        "left": 11
      },
      "borderBoxWidth": 122,
      "borderBoxHeight": 92,
      "outerWidth": 137,
      "outerHeight": 92
    },
    "node-6": {
      "id": "node-6",
      "x": 169,
      "y": 23,
      "width": 60,
      "height": 35,
      "padding": {
        "top": 3,
        "right": 6,
        "bottom": 13,
        "left": 19
      },
      "border": {
        "top": 0,
        "right": 2,
        "bottom": 10,
        "left": 2
      },
      "margin": {
        "top": 0,
        "right": 20,
        "bottom": 0,
        "left": 11
      },
      "borderBoxWidth": 89,
      "borderBoxHeight": 61,
      "outerWidth": 120,
      "outerHeight": 61
    },
    "node-7": {
      "id": "node-7",
      "x": 167,
      "y": 84,
      "width": 23,
      "height": 26,
      "padding": {
        "top": 17,
        "right": 5,
        "bottom": 16,
        "left": 11
      },
      "border": {
        "top": 8,
        "right": 1,
        "bottom": 6,
        "left": 6
      },
      "margin": {
        "top": 0,
        "right": 14,
        "bottom": 0,
        "left": 9
      },
      "borderBoxWidth": 46,
      "borderBoxHeight": 73,
      "outerWidth": 69,
      "outerHeight": 73
    },
    "node-8": {
      "id": "node-8",
      "x": 275,
      "y": 13,
      "width": 119,
      "height": 120,
      "padding": {
        "top": 9,
        "right": 2,
        "bottom": 17,
        "left": 0
      },
      "border": {
        "top": 5,
        "right": 10,
        "bottom": 1,
        "left": 8
      },
      "margin": {
        "top": 0,
        "right": 6,
        "bottom": 0,
        "left": 5
      },
      "borderBoxWidth": 139,
      "borderBoxHeight": 152,
      "outerWidth": 150,
      "outerHeight": 152
    },
    "node-9": {
      "id": "node-9",
      "x": 283,
      "y": 27,
      "width": 85,
      "height": 21,
      "padding": {
        "top": 20,
        "right": 18,
        "bottom": 16,
        "left": 9
      },
      "border": {
        "top": 0,
        "right": 7,
        "bottom": 6,
        "left": 10
      },
      "margin": {
        "top": 0,
        "right": 17,
        "bottom": 0,
        "left": 0
      },
      "borderBoxWidth": 129,
      "borderBoxHeight": 63,
      "outerWidth": 146,
      "outerHeight": 63
    },
    "node-10": {
      "id": "node-10",
      "x": 296,
      "y": 90,
      "width": 24,
      "height": 79,
      "padding": {
        "top": 8,
        "right": 11,
        "bottom": 13,
        "left": 16
      },
      "border": {
        "top": 6,
        "right": 3,
        "bottom": 10,
        "left": 0
      },
      "margin": {
        "top": 0,
        "right": 5,
        "bottom": 0,
        "left": 13
      },
      "borderBoxWidth": 54,
      "borderBoxHeight": 116,
      "outerWidth": 72,
      "outerHeight": 116
    }
  },
  "chromiumVersion": "Chrome/146.0.7680.153",
  "tolerance": 0.5
}